{
  "@context": "https://schema.org/",
  "@type": "Dataset",
  "name": "Power Spectral Density Values",
  "description": "Output values from a standardized FDSN PSD web service",
  "url": "https://service.earthscope.org/fdsnws/psd/psd?...",
  "version": "2025-05-22T10:09:00Z",
  "isAccessibleForFree": true,
  "keywords": [
    {
      "@type": "DefinedTerm",
      "name": "seismology",
      "inDefinedTermSet": "https://apps.usgs.gov/thesaurus/",
      "url": "https://apps.usgs.gov/thesaurus/term-simple.php?thcode=2&code=1050",
      "termCode": "thcode=2&code=1050"
    }
  ],
  "identifier": {
    "@id": "https://doi.org/...",
    "@type": "PropertyValue",
    "propertyID": "https://registry.identifiers.org/registry/doi",
    "value": "doi:...",
    "url": "https://doi.org/..."
  },
  "license": ["https://creativecommons.org/licenses/by/4.0/"],
  "variableMeasured": [
    {
      "@type": "PropertyValue",
      "name": "frequency",
      "propertyID":"http://purl.obolibrary.org/obo/...",
      "url": "Optionnal : not intended to be machine-actionable",
      "description": "PSD output is in 'frequency'",
      "measurementTechnique": "https://...",
      "unitText": "herz",
      "unitCode":"http://qudt.org/vocab/unit/HZ",
      "minValue": "Optionnal",
      "maxValue": "Optionnal"
    },
    {
      "@type": "PropertyValue",
      "name": "power",
      "propertyID":"http://purl.obolibrary.org/obo/...",
      "url": "Optionnal : not intended to be machine-actionable",
      "description": "power ratio formula, e.g., '10log10(m**2/sec**4/Hz)'",
      "measurementTechnique": "https://...",
      "unitText": "decibels",
      "unitCode":"http://qudt.org/vocab/unit/Decib",
      "minValue": "Optionnal",
      "maxValue": "Optionnal"
    }
  ]
}
